clinja/__init__.py
clinja/cli.py
clinja/clinja.py
clinja/completions.py
clinja/settings.py
clinja/utils.py
clinja-1.2.2.dist-info/entry_points.txt
clinja-1.2.2.dist-info/LICENSE
clinja-1.2.2.dist-info/WHEEL
clinja-1.2.2.dist-info/METADATA
clinja-1.2.2.dist-info/RECORD
