Metadata-Version: 2.1
Name: clinja
Version: 1.2.2
Summary: A jinja command line interface
Home-page: https://github.com/loiccoyle/clinja
License: MIT
Keywords: jinja,cli,templates
Author: Loic Coyle
Author-email: loic.coyle@hotmail.fr
Requires-Python: >=3.6,<4.0
Classifier: License :: OSI Approved :: MIT License
Classifier: Operating System :: MacOS
Classifier: Operating System :: Microsoft :: Windows
Classifier: Operating System :: Unix
Classifier: Programming Language :: Python
Classifier: Programming Language :: Python :: 3
Classifier: Programming Language :: Python :: 3.6
Classifier: Programming Language :: Python :: 3.7
Classifier: Programming Language :: Python :: 3.8
Classifier: Programming Language :: Python :: 3.9
Classifier: Topic :: Text Processing
Classifier: Topic :: Utilities
Requires-Dist: Jinja2 (>=3.0.1,<4.0.0)
Requires-Dist: click (>=8.0.1,<9.0.0)
Requires-Dist: myopy (>=1.0,<2.0)
Project-URL: Repository, https://github.com/loiccoyle/clinja
